meegkit/__init__.py
meegkit/asr.py
meegkit/cca.py
meegkit/detrend.py
meegkit/dss.py
meegkit/lof.py
meegkit/ress.py
meegkit/sns.py
meegkit/star.py
meegkit/trca.py
meegkit/tspca.py
meegkit/utils/__init__.py
meegkit/utils/asr.py
meegkit/utils/auditory.py
meegkit/utils/base.py
meegkit/utils/covariances.py
meegkit/utils/denoise.py
meegkit/utils/matrix.py
meegkit/utils/sig.py
meegkit/utils/stats.py
meegkit/utils/testing.py
meegkit/utils/trca.py
meegkit-0.1.7.dist-info/LICENSE
meegkit-0.1.7.dist-info/METADATA
meegkit-0.1.7.dist-info/WHEEL
meegkit-0.1.7.dist-info/top_level.txt
meegkit-0.1.7.dist-info/RECORD
