Metadata-Version: 2.1
Name: meegkit
Version: 0.1.7
Summary: M/EEG denoising in Python
Author-email: Nicolas Barascud <nicolas.barascud@gmail.com>
License: BSD (3-clause)
Project-URL: repository, https://github.com/nbara/python-meegkit
Project-URL: documentation, https://nbara.github.io/python-meegkit/
Project-URL: tracker, https://github.com/nbara/python-meegkit/issues/
Requires-Python: >=3.8
License-File: LICENSE
Requires-Dist: numpy >=1.20
Requires-Dist: scipy
Requires-Dist: matplotlib
Requires-Dist: scikit-learn
Requires-Dist: pandas
Requires-Dist: joblib
Requires-Dist: tqdm
Requires-Dist: statsmodels
Requires-Dist: pyriemann >=0.2.7
Provides-Extra: docs
Requires-Dist: sphinx ; extra == 'docs'
Requires-Dist: sphinx-gallery ; extra == 'docs'
Requires-Dist: sphinx-bootstrap-theme ; extra == 'docs'
Requires-Dist: sphinx-copybutton ; extra == 'docs'
Requires-Dist: sphinxemoji ; extra == 'docs'
Requires-Dist: numpydoc ; extra == 'docs'
Requires-Dist: pydata-sphinx-theme ; extra == 'docs'
Requires-Dist: pillow ; extra == 'docs'
Requires-Dist: jupyter-sphinx ; extra == 'docs'
Requires-Dist: ghp-import ; extra == 'docs'
Requires-Dist: meegkit[extra] ; extra == 'docs'
Provides-Extra: extra
Requires-Dist: pymanopt ; extra == 'extra'
Provides-Extra: tests
Requires-Dist: pytest ; extra == 'tests'
Requires-Dist: pytest-cov ; extra == 'tests'
Requires-Dist: codecov ; extra == 'tests'
Requires-Dist: codespell ; extra == 'tests'
Requires-Dist: ruff ; extra == 'tests'
Requires-Dist: meegkit[extra] ; extra == 'tests'
